Workbook

Sheet How It Works
B2: Ballpark: daily estimation game
B3: Five questions a day. Guess the number. Hit it out of the park.
B5: Days in this file | C5: =MAX('Daily Questions'!A2:A1501)
B6: Questions in this file | C6: =COUNTA('Daily Questions'!E2:E1501)
B7: First day | C7: ='Daily Questions'!B2
B8: Last day | C8: =MAX('Daily Questions'!B2:B1501)
B9: Repeated categories on any day | C9: =IF(MAX('Daily Questions'!L2:L1501)=1,"None. Every day has 5 different categories.","Check the red rows in Daily Questions")
B10: Daily format | C10: Questions 1 to 4 come from 10 rotating categories (Geography, Sports, Space and Science, Animals and Nature, Human Body, Buildings and Engineering, Movies Music and Games, History, Canada, Food and Everyday Life), never more than one per category in a day, and the same category is avoided on back-to-back days where possible. Questions are ordered easy to hard. Question 5 is always the Distance of the Day.
B11: How the game picks today's set | C11: The game counts days since the first date in this file. Day 1 = first date. If you launch later, just change the start date in the game, the order stays the same.
B12: Scoring | C12: See the Scoring tab. Closeness is a ratio (bigger divided by smaller), so guessing double the answer counts the same as guessing half. Within 10% clears the wall (400+ ft). Up to 3 swings per question in Classic mode; Easy mode is scored separately as right, close or wrong.
B13: Why there are no 'what year' questions | C13: Ratio scoring breaks on years. Guessing 1950 when the answer is 1969 is only 1% off, which would score 90. Every answer here is a positive amount where percent off is meaningful.
B14: Answers | C14: Rounded to a sensible precision. Use the rounded value shown as the 'exact' answer. Some facts (animal sizes, food stats, estimates) are commonly quoted averages, so the Source to Check column says where to confirm.
B15: Before launch | C15: Spot check the answers, especially the Hard ones, and mark the Verified column. Fix anything flagged before that day goes live. Days 90 to 300 (Jan 2 to Jul 31, 2027) were added in Oct 2026 and are marked in the Notes column.
B16: Adding more days | C16: Add new rows at the bottom with the next Day numbers and dates, following the same 5-per-day pattern. The Category Repeats column turns red if a day has two questions from the same category.

Sheet Scoring
A1: Hit | B1: Guess within | C1: Points | D1: Feet | F1: Try it
A2: Out of the park | B2: 10% | C2: 89 to 100 | D2: 400 to 450 | F2: Real answer | G2: 3359
A3: Deep to the wall | B3: 25% | C3: 67 to 88 | D3: 300 to 400 | F3: Your guess | G3: 3000
A4: Solid hit | B4: 50% | C4: 45 to 66 | D4: 200 to 300 | F4: How far off (ratio) | G4: =IFERROR(MAX(G2,G3)/MIN(G2,G3),"")
A5: In play | B5: 2x | C5: 23 to 44 | D5: 100 to 200 | F5: Hit | G5: =IF(G4="","",IF(G4<=1.1,"Out of the park",IF(G4<=1.25,"Deep to the wall",IF(G4<=1.5,"Solid hit",IF(G4<=2,"In play",IF(G4<=4,"Caught","Swing and a miss"))))))
A6: Caught | B6: 4x | C6: 1 to 22 | D6: under 100
A7: Swing and a miss | B7: more than 4x | C7: 0 | D7: 0 | F7: Change the blue cells to test. Each extra swing is worth 15% less (then 30%), and a hint costs 15%.
F9: Max possible per day | G9: 2,250 ft (450 per question)

Sheet Daily Questions
A1: Day | B1: Date | C1: Q# | D1: Category | E1: Question | F1: Answer | G1: Unit | H1: Difficulty | I1: Source to Check | J1: Verified? | K1: Notes | L1: Category Repeats (must be 1)
A2: 1 | B2: 46300 | C2: 1 | D2: Buildings and Engineering | E2: How tall is the Hoover Dam? | F2: 221 | G2: metres | H2: Medium | I2: US Bureau of Reclamation | L2: =COUNTIFS($A$2:$A$1501,A2,$D$2:$D$1501,D2)
A3: 1 | B3: 46300 | C3: 2 | D3: Movies, Music and Games | E3: How long is The Godfather? | F3: 175 | G3: minutes | H3: Medium | I3: IMDb | L3: =COUNTIFS($A$2:$A$1501,A3,$D$2:$D$1501,D3)
A4: 1 | B4: 46300 | C4: 3 | D4: Geography | E4: How tall is Aconcagua, the highest mountain in South America? | F4: 6961 | G4: metres | H4: Hard | I4: Britannica / national survey agencies | L4: =COUNTIFS($A$2:$A$1501,A4,$D$2:$D$1501,D4)
A5: 1 | B5: 46300 | C5: 4 | D5: Sports | E5: How many consecutive games did Cal Ripken Jr. play? | F5: 2632 | G5: games | H5: Hard | I5: MLB.com | L5: =COUNTIFS($A$2:$A$1501,A5,$D$2:$D$1501,D5)
A6: 1 | B6: 46300 | C6: 5 | D6: Distance of the Day | E6: How far is it in a straight line from Iqaluit to New York? | F6: 2590 | G6: km | H6: Medium | I6: Computed great-circle distance (city centre to city centre) | L6: =COUNTIFS($A$2:$A$1501,A6,$D$2:$D$1501,D6)
A7: 2 | B7: 46301 | C7: 1 | D7: Animals and Nature | E7: How many eggs does a modern laying hen produce in a year? | F7: 300 | G7: eggs | H7: Medium | I7: Britannica / National Geographic / Guinness World Records | L7: =COUNTIFS($A$2:$A$1501,A7,$D$2:$D$1501,D7)
A8: 2 | B8: 46301 | C8: 2 | D8: Canada | E8: How many litres of maple sap does it take to make 1 litre of maple syrup? | F8: 40 | G8: litres | H8: Medium | I8: Natural Resources Canada / Statistics Canada / Parks Canada | L8: =COUNTIFS($A$2:$A$1501,A8,$D$2:$D$1501,D8)
A9: 2 | B9: 46301 | C9: 3 | D9: Space and Science | E9: How many centimetres does the Moon drift away from Earth each year? | F9: 3.8 | G9: cm | H9: Hard | I9: NASA | L9: =COUNTIFS($A$2:$A$1501,A9,$D$2:$D$1501,D9)
A10: 2 | B10: 46301 | C10: 4 | D10: History | E10: How long was the Oregon Trail? | F10: 3490 | G10: km | H10: Hard | I10: US National Park Service | L10: =COUNTIFS($A$2:$A$1501,A10,$D$2:$D$1501,D10)
A11: 2 | B11: 46301 | C11: 5 | D11: Distance of the Day | E11: How far is it in a straight line from Karachi to Singapore? | F11: 4740 | G11: km | H11: Medium | I11: Computed great-circle distance (city centre to city centre) | L11: =COUNTIFS($A$2:$A$1501,A11,$D$2:$D$1501,D11)
A12: 3 | B12: 46302 | C12: 1 | D12: Buildings and Engineering | E12: How tall was the Saturn V rocket that launched Apollo 11? | F12: 111 | G12: metres | H12: Medium | I12: NASA | L12: =COUNTIFS($A$2:$A$1501,A12,$D$2:$D$1501,D12)
A13: 3 | B13: 46302 | C13: 2 | D13: Sports | E13: How many Stanley Cups have the Montreal Canadiens won? | F13: 24 | G13: Stanley Cups | H13: Medium | I13: NHL Records | L13: =COUNTIFS($A$2:$A$1501,A13,$D$2:$D$1501,D13)
... A177: 36 | B177: 46335 | C177: 1 | D177: Food and Everyday Life | E177: How many grams of sugar are in a 355 mL can of Coca-Cola? | F177: 39 | G177: grams | H177: Easy | I177: Coca-Cola | L177: =COUNTIFS($A$2:$A$1501,A177,$D$2:$D$1501,D177)
A178: 36 | B178: 46335 | C178: 2 | D178: Space and Science | E178: What is the atomic number of uranium? | F178: 92 | H178: Medium | I178: IUPAC | L178: =COUNTIFS($A$2:$A$1501,A178,$D$2:$D$1501,D178)
A179: 36 | B179: 46335 | C179: 3 | D179: Human Body | E179: How long is the adult spinal cord? | F179: 45 | G179: cm | H179: Hard | I179: Cleveland Clinic / NIH / Guinness World Records | L179: =COUNTIFS($A$2:$A$1501,A179,$D$2:$D$1501,D179)
A180: 36 | B180: 46335 | C180: 4 | D180: Animals and Nature | E180: How many times per second does a honeybee beat its wings? | F180: 230 | G180: beats | H180: Hard | I180: Britannica / National Geographic / Guinness World Records | L180: =COUNTIFS($A$2:$A$1501,A180,$D$2:$D$1501,D180)
A181: 36 | B181: 46335 | C181: 5 | D181: Distance of the Day | E181: How far is it in a straight line from Miami to Nairobi? | F181: 12760 | G181: km | H181: Hard | I181: Computed great-circle distance (city centre to city centre) | L181: =COUNTIFS($A$2:$A$1501,A181,$D$2:$D$1501,D181)
A182: 37 | B182: 46336 | C182: 1 | D182: Movies, Music and Games | E182: How many sonnets did Shakespeare write? | F182: 154 | G182: sonnets | H182: Medium | I182: IMDb / official records / Guinness World Records | L182: =COUNTIFS($A$2:$A$1501,A182,$D$2:$D$1501,D182)
A183: 37 | B183: 46336 | C183: 2 | D183: Geography | E183: How long is the Great Wall of China, counting all its branches? | F183: 21196 | G183: km | H183: Hard | I183: China State Administration of Cultural Heritage 2012 | L183: =COUNTIFS($A$2:$A$1501,A183,$D$2:$D$1501,D183)
A184: 37 | B184: 46336 | C184: 3 | D184: Buildings and Engineering | E184: How long is the Gotthard Base Tunnel in Switzerland, the world's longest rail tunnel? | F184: 57 | G184: km | H184: Hard | I184: SBB | L184: =COUNTIFS($A$2:$A$1501,A184,$D$2:$D$1501,D184)
A185: 37 | B185: 46336 | C185: 4 | D185: Sports | E185: How many hits did Ichiro Suzuki get in his record 2004 season? | F185: 262 | G185: hits | H185: Hard | I185: MLB.com | L185: =COUNTIFS($A$2:$A$1501,A185,$D$2:$D$1501,D185)
A186: 37 | B186: 46336 | C186: 5 | D186: Distance of the Day | E186: How far is it in a straight line from Ottawa to Buenos Aires? | F186: 9070 | G186: km | H186: Hard | I186: Computed great-circle distance (city centre to city centre) | L186: =COUNTIFS($A$2:$A$1501,A186,$D$2:$D$1501,D186)
A187: 38 | B187: 46337 | C187: 1 | D187: Space and Science | E187: How many elements are on the periodic table? | F187: 118 | G187: elements | H187: Easy | I187: IUPAC | L187: =COUNTIFS($A$2:$A$1501,A187,$D$2:$D$1501,D187)
A188: 38 | B188: 46337 | C188: 2 | D188: History | E188: How many years did Queen Elizabeth II reign? | F188: 70 | G188: years | H188: Easy | I188: Britannica / national archives | L188: =COUNTIFS($A$2:$A$1501,A188,$D$2:$D$1501,D188)
A189: 38 | B189: 46337 | C189: 3 | D189: Canada | E189: How many steps are in the CN Tower's stairwell? | F189: 1776 | G189: steps | H189: Hard | I189: CN Tower | L189: =COUNTIFS($A$2:$A$1501,A189,$D$2:$D$1501,D189)
A190: 38 | B190: 46337 | C190: 4 | D190: Human Body | E190: How many sweat glands does the average person have? | F190: 3000000 | G190: sweat glands | H190: Hard | I190: Cleveland Clinic / NIH / Guinness World Records | L190: =COUNTIFS($A$2:$A$1501,A190,$D$2:$D$1501,D190)
... A216: 43 | B216: 46342 | C216: 5 | D216: Distance of the Day | E216: How far is it in a straight line from Whitehorse to Karachi? | F216: 10290 | G216: km | H216: Hard | I216: Computed great-circle distance (city centre to city centre) | L216: =COUNTIFS($A$2:$A$1501,A216,$D$2:$D$1501,D216)
A217: 44 | B217: 46343 | C217: 1 | D217: Space and Science | E217: What is the atomic number of gold? | F217: 79 | H217: Medium | I217: IUPAC | L217: =COUNTIFS($A$2:$A$1501,A217,$D$2:$D$1501,D217)
A218: 44 | B218: 46343 | C218: 2 | D218: Canada | E218: What percentage of the world's maple syrup comes from Quebec? | F218: 72 | G218: % | H218: Medium | I218: Quebec Maple Syrup Producers | L218: =COUNTIFS($A$2:$A$1501,A218,$D$2:$D$1501,D218)
A219: 44 | B219: 46343 | C219: 3 | D219: Food and Everyday Life | E219: How much caffeine is in a single shot of espresso? | F219: 63 | G219: mg | H219: Medium | I219: USDA | L219: =COUNTIFS($A$2:$A$1501,A219,$D$2:$D$1501,D219)
A220: 44 | B220: 46343 | C220: 4 | D220: Animals and Nature | E220: What is the hottest air temperature ever recorded on Earth? | F220: 56.7 | G220: °C | H220: Medium | I220: World Meteorological Organization | L220: =COUNTIFS($A$2:$A$1501,A220,$D$2:$D$1501,D220)
A221: 44 | B221: 46343 | C221: 5 | D221: Distance of the Day | E221: How far is it in a straight line from Lahore to Seoul? | F221: 4800 | G221: km | H221: Medium | I221: Computed great-circle distance (city centre to city centre) | L221: =COUNTIFS($A$2:$A$1501,A221,$D$2:$D$1501,D221)
A222: 45 | B222: 46344 | C222: 1 | D222: Geography | E222: How tall is Mount Fuji? | F222: 3776 | G222: metres | H222: Medium | I222: Britannica / national survey agencies | L222: =COUNTIFS($A$2:$A$1501,A222,$D$2:$D$1501,D222)
A223: 45 | B223: 46344 | C223: 2 | D223: Movies, Music and Games | E223: How long is Shrek? | F223: 90 | G223: minutes | H223: Medium | I223: IMDb | L223: =COUNTIFS($A$2:$A$1501,A223,$D$2:$D$1501,D223)
A224: 45 | B224: 46344 | C224: 3 | D224: Buildings and Engineering | E224: How tall is the Shanghai Tower? | F224: 632 | G224: metres | H224: Hard | I224: CTBUH | L224: =COUNTIFS($A$2:$A$1501,A224,$D$2:$D$1501,D224)
A225: 45 | B225: 46344 | C225: 4 | D225: Sports | E225: How many rushing yards did Eric Dickerson gain in his record 1984 season? | F225: 2105 | G225: yards | H225: Hard | I225: NFL.com | L225: =COUNTIFS($A$2:$A$1501,A225,$D$2:$D$1501,D225)
A226: 45 | B226: 46344 | C226: 5 | D226: Distance of the Day | E226: How far is it in a straight line from Halifax to Seoul? | F226: 10810 | G226: km | H226: Hard | I226: Computed great-circle distance (city centre to city centre) | L226: =COUNTIFS($A$2:$A$1501,A226,$D$2:$D$1501,D226)
A227: 46 | B227: 46345 | C227: 1 | D227: Space and Science | E227: What is the atomic number of silver? | F227: 47 | H227: Medium | I227: IUPAC | L227: =COUNTIFS($A$2:$A$1501,A227,$D$2:$D$1501,D227)
A228: 46 | B228: 46345 | C228: 2 | D228: Food and Everyday Life | E228: How many teaspoons are in one cup? | F228: 48 | G228: teaspoons | H228: Medium | I228: Food industry bodies / USDA / Water Footprint Network | L228: =COUNTIFS($A$2:$A$1501,A228,$D$2:$D$1501,D228)
A229: 46 | B229: 46345 | C229: 3 | D229: Animals and Nature | E229: How long is the Great Barrier Reef? | F229: 2300 | G229: km | H229: Medium | I229: Great Barrier Reef Marine Park Authority | L229: =COUNTIFS($A$2:$A$1501,A229,$D$2:$D$1501,D229)
A230: 46 | B230: 46345 | C230: 4 | D230: History | E230: How many houses were destroyed in the Great Fire of London in 1666? | F230: 13200 | G230: houses | H230: Hard | I230: Museum of London | L230: =COUNTIFS($A$2:$A$1501,A230,$D$2:$D$1501,D230)
A231: 46 | B231: 46345 | C231: 5 | D231: Distance of the Day | E231: How far is it in a straight line from Honolulu to Cape Town? | F231: 18570 | G231: km | H231: Hard | I231: Computed great-circle distance (city centre to city centre) | L231: =COUNTIFS($A$2:$A$1501,A231,$D$2:$D$1501,D231)
A232: 47 | B232: 46346 | C232: 1 | D232: Buildings and Engineering | E232: How tall is the Christ the Redeemer statue, not counting its pedestal? | F232: 30 | G232: metres | H232: Medium | I232: Official operator sites / CTBUH / Britannica | L232: =COUNTIFS($A$2:$A$1501,A232,$D$2:$D$1501,D232)
A233: 47 | B233: 46346 | C233: 2 | D233: Sports | E233: How many perfect 10s did Nadia Comaneci score at the 1976 Olympics? | F233: 7 | G233: perfect 10s | H233: Medium | I233: Olympics.com | L233: =COUNTIFS($A$2:$A$1501,A233,$D$2:$D$1501,D233)
A234: 47 | B234: 46346 | C234: 3 | D234: Movies, Music and Games | E234: How long is Avengers: Endgame? | F234: 181 | G234: minutes | H234: Medium | I234: IMDb | L234: =COUNTIFS($A$2:$A$1501,A234,$D$2:$D$1501,D234)
A235: 47 | B235: 46346 | C235: 4 | D235: Geography | E235: How big is the Sahara Desert? | F235: 9200000 | G235: km² | H235: Hard | I235: Britannica / national survey agencies | L235: =COUNTIFS($A$2:$A$1501,A235,$D$2:$D$1501,D235)
A236: 47 | B236: 46346 | C236: 5 | D236: Distance of the Day | E236: How far is it in a straight line from St. John's to Karachi? | F236: 9960 | G236: km | H236: Hard | I236: Computed great-circle distance (city centre to city centre) | L236: =COUNTIFS($A$2:$A$1501,A236,$D$2:$D$1501,D236)
A237: 48 | B237: 46347 | C237: 1 | D237: Space and Science | E237: How old is Earth? | F237: 4.54 | G237: billion years | H237: Medium | I237: USGS | L237: =COUNTIFS($A$2:$A$1501,A237,$D$2:$D$1501,D237)
A238: 48 | B238: 46347 | C238: 2 | D238: Canada | E238: How many islands make up the Thousand Islands? | F238: 1864 | G238: islands | H238: Medium | I238: Natural Resources Canada / Statistics Canada / Parks Canada | L238: =COUNTIFS($A$2:$A$1501,A238,$D$2:$D$1501,D238)
A239: 48 | B239: 46347 | C239: 3 | D239: History | E239: How many people died when the Titanic sank? | F239: 1500 | G239: people | H239: Medium | I239: Britannica / national archives | L239: =COUNTIFS($A$2:$A$1501,A239,$D$2:$D$1501,D239)
... A444: 89 | B444: 46388 | C444: 3 | D444: History | E444: How many years did the Byzantine Empire last, from the founding of Constantinople to its fall? | F444: 1123 | G444: years | H444: Hard | I444: Britannica / national archives | L444: =COUNTIFS($A$2:$A$1501,A444,$D$2:$D$1501,D444)
A445: 89 | B445: 46388 | C445: 4 | D445: Space and Science | E445: What is the atomic number of lead? | F445: 82 | H445: Hard | I445: IUPAC | L445: =COUNTIFS($A$2:$A$1501,A445,$D$2:$D$1501,D445)
A446: 89 | B446: 46388 | C446: 5 | D446: Distance of the Day | E446: How far is it in a straight line from Iqaluit to Madrid? | F446: 4840 | G446: km | H446: Medium | I446: Computed great-circle distance (city centre to city centre) | L446: =COUNTIFS($A$2:$A$1501,A446,$D$2:$D$1501,D446)
A447: 90 | B447: 46389 | C447: 1 | D447: Sports | E447: How many bases are on a baseball diamond, including home plate? | F447: 4 | G447: bases | H447: Easy | I447: MLB rulebook | K447: Added Oct 2026. Spot check before this day goes live. | L447: =COUNTIFS($A$2:$A$1501,A447,$D$2:$D$1501,D447)
A448: 90 | B448: 46389 | C448: 2 | D448: Space and Science | E448: How old is the Sun? | F448: 4.6 | G448: billion years | H448: Medium | I448: NASA | K448: Added Oct 2026. Spot check before this day goes live. | L448: =COUNTIFS($A$2:$A$1501,A448,$D$2:$D$1501,D448)
A449: 90 | B449: 46389 | C449: 3 | D449: Movies, Music and Games | E449: How long is Spider-Man: No Way Home? | F449: 148 | G449: minutes | H449: Medium | I449: IMDb | K449: Added Oct 2026. Spot check before this day goes live. | L449: =COUNTIFS($A$2:$A$1501,A449,$D$2:$D$1501,D449)
A450: 90 | B450: 46389 | C450: 4 | D450: Geography | E450: How tall are the Iguazu Falls at their highest? | F450: 82 | G450: metres | H450: Hard | I450: UNESCO | K450: Added Oct 2026. Spot check before this day goes live. | L450: =COUNTIFS($A$2:$A$1501,A450,$D$2:$D$1501,D450)
A451: 90 | B451: 46389 | C451: 5 | D451: Distance of the Day | E451: How far is it in a straight line from New Orleans to Oslo? | F451: 7730 | G451: km | H451: Medium | I451: Computed great-circle distance (city centre to city centre) | L451: =COUNTIFS($A$2:$A$1501,A451,$D$2:$D$1501,D451)
A452: 91 | B452: 46390 | C452: 1 | D452: Food and Everyday Life | E452: How cold should a home freezer be, in degrees below zero? | F452: 18 | G452: °C | H452: Medium | I452: Health Canada | K452: Added Oct 2026. Spot check before this day goes live. | L452: =COUNTIFS($A$2:$A$1501,A452,$D$2:$D$1501,D452)
A453: 91 | B453: 46390 | C453: 2 | D453: Animals and Nature | E453: How long can a Komodo dragon grow? | F453: 3 | G453: metres | H453: Medium | I453: Smithsonian National Zoo | K453: Added Oct 2026. Spot check before this day goes live. | L453: =COUNTIFS($A$2:$A$1501,A453,$D$2:$D$1501,D453)
A454: 91 | B454: 46390 | C454: 3 | D454: History | E454: How many days did the Battle of Stalingrad last, roughly? | F454: 200 | G454: days | H454: Hard | I454: Britannica | K454: Added Oct 2026. Spot check before this day goes live. | L454: =COUNTIFS($A$2:$A$1501,A454,$D$2:$D$1501,D454)
A455: 91 | B455: 46390 | C455: 4 | D455: Buildings and Engineering | E455: How long is the Tsing Ma Bridge's main span in Hong Kong? | F455: 1377 | G455: metres | H455: Hard | I455: Hong Kong Highways Department | K455: Added Oct 2026. Spot check before this day goes live. | L455: =COUNTIFS($A$2:$A$1501,A455,$D$2:$D$1501,D455)
A456: 91 | B456: 46390 | C456: 5 | D456: Distance of the Day | E456: How far is it in a straight line from Victoria to Addis Ababa? | F456: 13390 | G456: km | H456: Hard | I456: Computed great-circle distance (city centre to city centre) | L456: =COUNTIFS($A$2:$A$1501,A456,$D$2:$D$1501,D456)
A457: 92 | B457: 46391 | C457: 1 | D457: Sports | E457: How many minutes long is a round in professional boxing? | F457: 3 | G457: minutes | H457: Easy | I457: Boxing commissions | K457: Added Oct 2026. Spot check before this day goes live. | L457: =COUNTIFS($A$2:$A$1501,A457,$D$2:$D$1501,D457)
A458: 92 | B458: 46391 | C458: 2 | D458: Space and Science | E458: How hot is the core of the Sun? | F458: 15 | G458: million °C | H458: Medium | I458: NASA | K458: Added Oct 2026. Spot check before this day goes live. | L458: =COUNTIFS($A$2:$A$1501,A458,$D$2:$D$1501,D458)
A459: 92 | B459: 46391 | C459: 3 | D459: Movies, Music and Games | E459: How many episodes of Mad Men were made? | F459: 92 | G459: episodes | H459: Hard | I459: AMC | K459: Added Oct 2026. Spot check before this day goes live. | L459: =COUNTIFS($A$2:$A$1501,A459,$D$2:$D$1501,D459)
A460: 92 | B460: 46391 | C460: 4 | D460: Geography | E460: How long is the Colorado River? | F460: 2330 | G460: km | H460: Hard | I460: US Geological Survey | K460: Added Oct 2026. Spot check before this day goes live. | L460: =COUNTIFS($A$2:$A$1501,A460,$D$2:$D$1501,D460)
A461: 92 | B461: 46391 | C461: 5 | D461: Distance of the Day | E461: How far is it in a straight line from Athens to Istanbul? | F461: 560 | G461: km | H461: Easy | I461: Computed great-circle distance (city centre to city centre) | L461: =COUNTIFS($A$2:$A$1501,A461,$D$2:$D$1501,D461)
A462: 93 | B462: 46392 | C462: 1 | D462: Food and Everyday Life | E462: How many digits are in a typical credit card number? | F462: 16 | G462: digits | H462: Easy | I462: ISO/IEC 7812 | K462: Added Oct 2026. Spot check before this day goes live. | L462: =COUNTIFS($A$2:$A$1501,A462,$D$2:$D$1501,D462)
A463: 93 | B463: 46392 | C463: 2 | D463: Animals and Nature | E463: How many teeth does an adult dog have? | F463: 42 | G463: teeth | H463: Medium | I463: American Veterinary Medical Association | K463: Added Oct 2026. Spot check before this day goes live. | L463: =COUNTIFS($A$2:$A$1501,A463,$D$2:$D$1501,D463)
A464: 93 | B464: 46392 | C464: 3 | D464: History | E464: How many days did the Cuban Missile Crisis last? | F464: 13 | G464: days | H464: Medium | I464: JFK Presidential Library | K464: Added Oct 2026. Spot check before this day goes live. | L464: =COUNTIFS($A$2:$A$1501,A464,$D$2:$D$1501,D464)
A465: 93 | B465: 46392 | C465: 4 | D465: Buildings and Engineering | E465: How tall is the Ostankino Tower in Moscow? | F465: 540 | G465: metres | H465: Hard | I465: CTBUH | K465: Added Oct 2026. Spot check before this day goes live. | L465: =COUNTIFS($A$2:$A$1501,A465,$D$2:$D$1501,D465)
A466: 93 | B466: 46392 | C466: 5 | D466: Distance of the Day | E466: How far is it in a straight line from Regina to Barcelona? | F466: 7580 | G466: km | H466: Medium | I466: Computed great-circle distance (city centre to city centre) | L466: =COUNTIFS($A$2:$A$1501,A466,$D$2:$D$1501,D466)
A467: 94 | B467: 46393 | C467: 1 | D467: Sports | E467: How many major golf championships did Jack Nicklaus win? | F467: 18 | G467: majors | H467: Medium | I467: PGA Tour | K467: Added Oct 2026. Spot check before this day goes live. | L467: =COUNTIFS($A$2:$A$1501,A467,$D$2:$D$1501,D467)
A468: 94 | B468: 46393 | C468: 2 | D468: Space and Science | E468: What is the atomic number of copper? | F468: 29 | H468: Medium | I468: IUPAC periodic table | K468: Added Oct 2026. Spot check before this day goes live. | L468: =COUNTIFS($A$2:$A$1501,A468,$D$2:$D$1501,D468)
A469: 94 | B469: 46393 | C469: 3 | D469: Movies, Music and Games | E469: How long is The Sound of Music? | F469: 172 | G469: minutes | H469: Hard | I469: IMDb | K469: Added Oct 2026. Spot check before this day goes live. | L469: =COUNTIFS($A$2:$A$1501,A469,$D$2:$D$1501,D469)
A470: 94 | B470: 46393 | C470: 4 | D470: Geography | E470: How big is the United Kingdom? | F470: 242495 | G470: km² | H470: Hard | I470: Office for National Statistics | K470: Added Oct 2026. Spot check before this day goes live. | L470: =COUNTIFS($A$2:$A$1501,A470,$D$2:$D$1501,D470)
A471: 94 | B471: 46393 | C471: 5 | D471: Distance of the Day | E471: How far is it in a straight line from Edmonton to Denver? | F471: 1660 | G471: km | H471: Medium | I471: Computed great-circle distance (city centre to city centre) | L471: =COUNTIFS($A$2:$A$1501,A471,$D$2:$D$1501,D471)
A472: 95 | B472: 46394 | C472: 1 | D472: Food and Everyday Life | E472: How many eggs are in two dozen? | F472: 24 | G472: eggs | H472: Easy | I472: Merriam-Webster | K472: Added Oct 2026. Spot check before this day goes live. | L472: =COUNTIFS($A$2:$A$1501,A472,$D$2:$D$1501,D472)
A473: 95 | B473: 46394 | C473: 2 | D473: Animals and Nature | E473: How many muscles are in an elephant's trunk? | F473: 40000 | G473: muscles | H473: Medium | I473: Smithsonian | K473: Added Oct 2026. Spot check before this day goes live. | L473: =COUNTIFS($A$2:$A$1501,A473,$D$2:$D$1501,D473)
A474: 95 | B474: 46394 | C474: 3 | D474: History | E474: How many days did the Montgomery Bus Boycott last? | F474: 381 | G474: days | H474: Hard | I474: US National Park Service | K474: Added Oct 2026. Spot check before this day goes live. | L474: =COUNTIFS($A$2:$A$1501,A474,$D$2:$D$1501,D474)
A475: 95 | B475: 46394 | C475: 4 | D475: Buildings and Engineering | E475: How long is the Lake Pontchartrain Causeway in Louisiana? | F475: 38.4 | G475: km | H475: Hard | I475: Guinness World Records | K475: Added Oct 2026. Spot check before this day goes live. | L475: =COUNTIFS($A$2:$A$1501,A475,$D$2:$D$1501,D475)
A476: 95 | B476: 46394 | C476: 5 | D476: Distance of the Day | E476: How far is it in a straight line from Fredericton to Beijing? | F476: 10460 | G476: km | H476: Hard | I476: Computed great-circle distance (city centre to city centre) | L476: =COUNTIFS($A$2:$A$1501,A476,$D$2:$D$1501,D476)
A477: 96 | B477: 46395 | C477: 1 | D477: Sports | E477: How many minutes long is a regulation NBA game? | F477: 48 | G477: minutes | H477: Easy | I477: NBA rulebook | K477: Added Oct 2026. Spot check before this day goes live. | L477: =COUNTIFS($A$2:$A$1501,A477,$D$2:$D$1501,D477)
A478: 96 | B478: 46395 | C478: 2 | D478: Space and Science | E478: How many times does the International Space Station orbit Earth each day? | F478: 16 | G478: orbits | H478: Medium | I478: NASA | K478: Added Oct 2026. Spot check before this day goes live. | L478: =COUNTIFS($A$2:$A$1501,A478,$D$2:$D$1501,D478)
A479: 96 | B479: 46395 | C479: 3 | D479: Movies, Music and Games | E479: How many episodes of The Big Bang Theory were made? | F479: 279 | G479: episodes | H479: Medium | I479: CBS | K479: Added Oct 2026. Spot check before this day goes live. | L479: =COUNTIFS($A$2:$A$1501,A479,$D$2:$D$1501,D479)
A480: 96 | B480: 46395 | C480: 4 | D480: Geography | E480: How big is Lake Huron? | F480: 59600 | G480: km² | H480: Hard | I480: US EPA Great Lakes | K480: Added Oct 2026. Spot check before this day goes live. | L480: =COUNTIFS($A$2:$A$1501,A480,$D$2:$D$1501,D480)
A481: 96 | B481: 46395 | C481: 5 | D481: Distance of the Day | E481: How far is it in a straight line from Seattle to San Francisco? | F481: 1090 | G481: km | H481: Easy | I481: Computed great-circle distance (city centre to city centre) | L481: =COUNTIFS($A$2:$A$1501,A481,$D$2:$D$1501,D481)
A482: 97 | B482: 46396 | C482: 1 | D482: Food and Everyday Life | E482: To what internal temperature should chicken be cooked to be safe? | F482: 74 | G482: °C | H482: Medium | I482: Health Canada | K482: Added Oct 2026. Spot check before this day goes live. | L482: =COUNTIFS($A$2:$A$1501,A482,$D$2:$D$1501,D482)
A483: 97 | B483: 46396 | C483: 2 | D483: Animals and Nature | E483: How many toes does a horse have on each foot? | F483: 1 | G483: toe | H483: Medium | I483: Britannica | K483: Added Oct 2026. Spot check before this day goes live. | L483: =COUNTIFS($A$2:$A$1501,A483,$D$2:$D$1501,D483)
A484: 97 | B484: 46396 | C484: 3 | D484: History | E484: How many people died aboard the Hindenburg? | F484: 36 | G484: people | H484: Hard | I484: Smithsonian | K484: Added Oct 2026. Spot check before this day goes live. | L484: =COUNTIFS($A$2:$A$1501,A484,$D$2:$D$1501,D484)
A485: 97 | B485: 46396 | C485: 4 | D485: Canada | E485: How deep is Great Slave Lake, the deepest lake in North America? | F485: 614 | G485: metres | H485: Hard | I485: Government of the Northwest Territories | K485: Added Oct 2026. Spot check before this day goes live. | L485: =COUNTIFS($A$2:$A$1501,A485,$D$2:$D$1501,D485)
A486: 97 | B486: 46396 | C486: 5 | D486: Distance of the Day | E486: How far is it in a straight line from Edmonton to Barcelona? | F486: 7810 | G486: km | H486: Medium | I486: Computed great-circle distance (city centre to city centre) | L486: =COUNTIFS($A$2:$A$1501,A486,$D$2:$D$1501,D486)
A487: 98 | B487: 46397 | C487: 1 | D487: Sports | E487: How high is the Olympic diving platform? | F487: 10 | G487: metres | H487: Easy | I487: World Aquatics | K487: Added Oct 2026. Spot check before this day goes live. | L487: =COUNTIFS($A$2:$A$1501,A487,$D$2:$D$1501,D487)
A488: 98 | B488: 46397 | C488: 2 | D488: Space and Science | E488: How many Space Shuttle orbiters flew in space? | F488: 5 | G488: orbiters | H488: Medium | I488: NASA | K488: Added Oct 2026. Spot check before this day goes live. | L488: =COUNTIFS($A$2:$A$1501,A488,$D$2:$D$1501,D488)
A489: 98 | B489: 46397 | C489: 3 | D489: Movies, Music and Games | E489: How long is The Lord of the Rings: The Fellowship of the Ring (theatrical cut)? | F489: 178 | G489: minutes | H489: Medium | I489: IMDb | K489: Added Oct 2026. Spot check before this day goes live. | L489: =COUNTIFS($A$2:$A$1501,A489,$D$2:$D$1501,D489)
A490: 98 | B490: 46397 | C490: 4 | D490: Geography | E490: How tall is Mount Olympus in Greece? | F490: 2917 | G490: metres | H490: Hard | I490: Britannica | K490: Added Oct 2026. Spot check before this day goes live. | L490: =COUNTIFS($A$2:$A$1501,A490,$D$2:$D$1501,D490)
A491: 98 | B491: 46397 | C491: 5 | D491: Distance of the Day | E491: How far is it in a straight line from Iqaluit to Accra? | F491: 8400 | G491: km | H491: Hard | I491: Computed great-circle distance (city centre to city centre) | L491: =COUNTIFS($A$2:$A$1501,A491,$D$2:$D$1501,D491)
A492: 99 | B492: 46398 | C492: 1 | D492: Food and Everyday Life | E492: How many cents are in a toonie? | F492: 200 | G492: cents | H492: Easy | I492: Royal Canadian Mint | K492: Added Oct 2026. Spot check before this day goes live. | L492: =COUNTIFS($A$2:$A$1501,A492,$D$2:$D$1501,D492)
...

Sheet Category Mix
A1: Category | B1: Questions | C1: Easy | D1: Medium | E1: Hard
A2: Animals and Nature | B2: =COUNTIF('Daily Questions'!$D$2:$D$1501,A2) | C2: =COUNTIFS('Daily Questions'!$D$2:$D$1501,A2,'Daily Questions'!$H$2:$H$1501,"Easy") | D2: =COUNTIFS('Daily Questions'!$D$2:$D$1501,A2,'Daily Questions'!$H$2:$H$1501,"Medium") | E2: =COUNTIFS('Daily Questions'!$D$2:$D$1501,A2,'Daily Questions'!$H$2:$H$1501,"Hard")
A3: Buildings and Engineering | B3: =COUNTIF('Daily Questions'!$D$2:$D$1501,A3) | C3: =COUNTIFS('Daily Questions'!$D$2:$D$1501,A3,'Daily Questions'!$H$2:$H$1501,"Easy") | D3: =COUNTIFS('Daily Questions'!$D$2:$D$1501,A3,'Daily Questions'!$H$2:$H$1501,"Medium") | E3: =COUNTIFS('Daily Questions'!$D$2:$D$1501,A3,'Daily Questions'!$H$2:$H$1501,"Hard")
A4: Canada | B4: =COUNTIF('Daily Questions'!$D$2:$D$1501,A4) | C4: =COUNTIFS('Daily Questions'!$D$2:$D$1501,A4,'Daily Questions'!$H$2:$H$1501,"Easy") | D4: =COUNTIFS('Daily Questions'!$D$2:$D$1501,A4,'Daily Questions'!$H$2:$H$1501,"Medium") | E4: =COUNTIFS('Daily Questions'!$D$2:$D$1501,A4,'Daily Questions'!$H$2:$H$1501,"Hard")
A5: Distance of the Day | B5: =COUNTIF('Daily Questions'!$D$2:$D$1501,A5) | C5: =COUNTIFS('Daily Questions'!$D$2:$D$1501,A5,'Daily Questions'!$H$2:$H$1501,"Easy") | D5: =COUNTIFS('Daily Questions'!$D$2:$D$1501,A5,'Daily Questions'!$H$2:$H$1501,"Medium") | E5: =COUNTIFS('Daily Questions'!$D$2:$D$1501,A5,'Daily Questions'!$H$2:$H$1501,"Hard")
A6: Food and Everyday Life | B6: =COUNTIF('Daily Questions'!$D$2:$D$1501,A6) | C6: =COUNTIFS('Daily Questions'!$D$2:$D$1501,A6,'Daily Questions'!$H$2:$H$1501,"Easy") | D6: =COUNTIFS('Daily Questions'!$D$2:$D$1501,A6,'Daily Questions'!$H$2:$H$1501,"Medium") | E6: =COUNTIFS('Daily Questions'!$D$2:$D$1501,A6,'Daily Questions'!$H$2:$H$1501,"Hard")
A7: Geography | B7: =COUNTIF('Daily Questions'!$D$2:$D$1501,A7) | C7: =COUNTIFS('Daily Questions'!$D$2:$D$1501,A7,'Daily Questions'!$H$2:$H$1501,"Easy") | D7: =COUNTIFS('Daily Questions'!$D$2:$D$1501,A7,'Daily Questions'!$H$2:$H$1501,"Medium") | E7: =COUNTIFS('Daily Questions'!$D$2:$D$1501,A7,'Daily Questions'!$H$2:$H$1501,"Hard")
A8: History | B8: =COUNTIF('Daily Questions'!$D$2:$D$1501,A8) | C8: =COUNTIFS('Daily Questions'!$D$2:$D$1501,A8,'Daily Questions'!$H$2:$H$1501,"Easy") | D8: =COUNTIFS('Daily Questions'!$D$2:$D$1501,A8,'Daily Questions'!$H$2:$H$1501,"Medium") | E8: =COUNTIFS('Daily Questions'!$D$2:$D$1501,A8,'Daily Questions'!$H$2:$H$1501,"Hard")
A9: Human Body | B9: =COUNTIF('Daily Questions'!$D$2:$D$1501,A9) | C9: =COUNTIFS('Daily Questions'!$D$2:$D$1501,A9,'Daily Questions'!$H$2:$H$1501,"Easy") | D9: =COUNTIFS('Daily Questions'!$D$2:$D$1501,A9,'Daily Questions'!$H$2:$H$1501,"Medium") | E9: =COUNTIFS('Daily Questions'!$D$2:$D$1501,A9,'Daily Questions'!$H$2:$H$1501,"Hard")
A10: Movies, Music and Games | B10: =COUNTIF('Daily Questions'!$D$2:$D$1501,A10) | C10: =COUNTIFS('Daily Questions'!$D$2:$D$1501,A10,'Daily Questions'!$H$2:$H$1501,"Easy") | D10: =COUNTIFS('Daily Questions'!$D$2:$D$1501,A10,'Daily Questions'!$H$2:$H$1501,"Medium") | E10: =COUNTIFS('Daily Questions'!$D$2:$D$1501,A10,'Daily Questions'!$H$2:$H$1501,"Hard")
A11: Space and Science | B11: =COUNTIF('Daily Questions'!$D$2:$D$1501,A11) | C11: =COUNTIFS('Daily Questions'!$D$2:$D$1501,A11,'Daily Questions'!$H$2:$H$1501,"Easy") | D11: =COUNTIFS('Daily Questions'!$D$2:$D$1501,A11,'Daily Questions'!$H$2:$H$1501,"Medium") | E11: =COUNTIFS('Daily Questions'!$D$2:$D$1501,A11,'Daily Questions'!$H$2:$H$1501,"Hard")
A12: Sports | B12: =COUNTIF('Daily Questions'!$D$2:$D$1501,A12) | C12: =COUNTIFS('Daily Questions'!$D$2:$D$1501,A12,'Daily Questions'!$H$2:$H$1501,"Easy") | D12: =COUNTIFS('Daily Questions'!$D$2:$D$1501,A12,'Daily Questions'!$H$2:$H$1501,"Medium") | E12: =COUNTIFS('Daily Questions'!$D$2:$D$1501,A12,'Daily Questions'!$H$2:$H$1501,"Hard")
A13: Total | B13: =SUM(B2:B12) | C13: =SUM(C2:C12) | D13: =SUM(D2:D12) | E13: =SUM(E2:E12)

Sheet Reserve
A1: Category | B1: Question | C1: Answer | D1: Unit | E1: Difficulty | F1: Source to Check | G1: Notes
A2: Animals and Nature | B2: How many legs does a spider have? | C2: 8 | D2: legs | E2: Easy | F2: National Geographic | G2: Spare question, not scheduled yet
A3: Human Body | B3: How many litres of air can adult lungs hold in total? | C3: 6 | D3: litres | E3: Medium | F3: American Lung Association | G3: Spare question, not scheduled yet
A4: Buildings and Engineering | B4: How tall is The Motherland Calls statue in Volgograd? | C4: 85 | D4: metres | E4: Hard | F4: Britannica | G4: Spare question, not scheduled yet
A5: Buildings and Engineering | B5: How long is the Hollywood Sign? | C5: 107 | D5: metres | E5: Hard | F5: Hollywood Sign Trust | G5: Spare question, not scheduled yet
A6: Canada | B6: How much snow does Montreal get in a typical year? | C6: 210 | D6: cm | E6: Hard | F6: Environment and Climate Change Canada | G6: Spare question, not scheduled yet
A7: Food and Everyday Life | B7: How many minutes does dried spaghetti usually take to cook? | C7: 10 | D7: minutes | E7: Easy | F7: Barilla | G7: Spare question, not scheduled yet
A8: Food and Everyday Life | B8: How many millilitres are in a tablespoon? | C8: 15 | D8: mL | E8: Medium | F8: Health Canada | G8: Spare question, not scheduled yet
A9: Geography | B9: How many countries share a land border with Russia? | C9: 14 | D9: countries | E9: Medium | F9: CIA World Factbook | G9: Spare question, not scheduled yet
A10: Geography | B10: How high above sea level is Lake Titicaca? | C10: 3812 | D10: metres | E10: Hard | F10: Britannica | G10: Spare question, not scheduled yet
A11: History | B11: How deep is the wreck of the Titanic? | C11: 3800 | D11: metres | E11: Medium | F11: NOAA | G11: Spare question, not scheduled yet
A12: Movies, Music and Games | B12: How long is The Matrix? | C12: 136 | D12: minutes | E12: Medium | F12: IMDb | G12: Spare question, not scheduled yet
A13: Movies, Music and Games | B13: How tall is an Oscar statuette? | C13: 34 | D13: cm | E13: Medium | F13: Academy of Motion Picture Arts and Sciences | G13: Spare question, not scheduled yet
A14: Space and Science | B14: What is the atomic number of oxygen? | C14: 8 | E14: Easy | F14: IUPAC periodic table | G14: Spare question, not scheduled yet
A15: Sports | B15: How long is one lap of the Indianapolis Motor Speedway? | C15: 2.5 | D15: miles | E15: Hard | F15: Indianapolis Motor Speedway | G15: Spare question, not scheduled yet
A16: Sports | B16: How many assists did John Stockton record in his NBA career? | C16: 15806 | D16: assists | E16: Hard | F16: NBA.com | G16: Spare question, not scheduled yet
